.coveragerc
.csslintrc
.isort.cfg
.jscs.json
CHANGES.rst
CONTRIBUTORS.rst
MANIFEST.in
README.rst
buildout.cfg
requirements.txt
setup.cfg
setup.py
travis.cfg
docs/LICENSE.GPL
docs/LICENSE.ZPL
docs/LICENSE.txt
plone/__init__.py
plone.recipe.codeanalysis.egg-info/PKG-INFO
plone.recipe.codeanalysis.egg-info/SOURCES.txt
plone.recipe.codeanalysis.egg-info/dependency_links.txt
plone.recipe.codeanalysis.egg-info/entry_points.txt
plone.recipe.codeanalysis.egg-info/namespace_packages.txt
plone.recipe.codeanalysis.egg-info/not-zip-safe
plone.recipe.codeanalysis.egg-info/requires.txt
plone.recipe.codeanalysis.egg-info/top_level.txt
plone/recipe/__init__.py
plone/recipe/codeanalysis/README.rst
plone/recipe/codeanalysis/__init__.py
plone/recipe/codeanalysis/analyser.py
plone/recipe/codeanalysis/chameleonlint.py
plone/recipe/codeanalysis/check_manifest.py
plone/recipe/codeanalysis/clean_lines.py
plone/recipe/codeanalysis/csslint.py
plone/recipe/codeanalysis/dependencychecker.py
plone/recipe/codeanalysis/flake8.py
plone/recipe/codeanalysis/i18ndude.py
plone/recipe/codeanalysis/importchecker.py
plone/recipe/codeanalysis/jscs.py
plone/recipe/codeanalysis/jshint.py
plone/recipe/codeanalysis/scsslint.py
plone/recipe/codeanalysis/testing.py
plone/recipe/codeanalysis/xmllint.py
plone/recipe/codeanalysis/zptlint.py
plone/recipe/codeanalysis/templates/pre-commit.tmpl
plone/recipe/codeanalysis/tests/__init__.py
plone/recipe/codeanalysis/tests/csslint.rst
plone/recipe/codeanalysis/tests/flake8.rst
plone/recipe/codeanalysis/tests/flake8_filesystem.rst
plone/recipe/codeanalysis/tests/i18ndude.rst
plone/recipe/codeanalysis/tests/jenkins.rst
plone/recipe/codeanalysis/tests/jscs.rst
plone/recipe/codeanalysis/tests/jshint.rst
plone/recipe/codeanalysis/tests/test_chameleon_lint.py
plone/recipe/codeanalysis/tests/test_check_manifest.py
plone/recipe/codeanalysis/tests/test_clean_lines.py
plone/recipe/codeanalysis/tests/test_csslint.py
plone/recipe/codeanalysis/tests/test_docs.py
plone/recipe/codeanalysis/tests/test_flake8.py
plone/recipe/codeanalysis/tests/test_i18ndude.py
plone/recipe/codeanalysis/tests/test_importchecker.py
plone/recipe/codeanalysis/tests/test_jscs.py
plone/recipe/codeanalysis/tests/test_jshint.py
plone/recipe/codeanalysis/tests/test_recipe.py
plone/recipe/codeanalysis/tests/test_script.py
plone/recipe/codeanalysis/tests/test_scsslint.py
