Metadata-Version: 1.1
Name: plone.recipe.codeanalysis
Version: 3.0.0
Summary: Static code analysis for buildout-based Python projects.
Home-page: http://github.com/plone/plone.recipe.codeanalysis/
Author: Timo Stollenwerk | kitconcept GmbH
Author-email: stollenwerk@kitconcept.com
License: GPL version 2
Platform: UNKNOWN
Classifier: Development Status :: 5 - Production/Stable
Classifier: Framework :: Buildout
Classifier: Intended Audience :: Developers
Classifier: License :: OSI Approved :: GNU General Public License (GPL)
Classifier: License :: OSI Approved :: GNU General Public License v2 (GPLv2)
Classifier: Operating System :: OS Independent
Classifier: Programming Language :: Python :: 2
Classifier: Programming Language :: Python :: 2.7
Classifier: Programming Language :: Python :: 3
Classifier: Programming Language :: Python :: 3.4
Classifier: Programming Language :: Python :: 3.5
Classifier: Programming Language :: Python :: 3.6
Classifier: Programming Language :: Python
Classifier: Topic :: Software Development :: Build Tools
